[
  {
    "id": 1,
    "name": "Clark Kent",
    "alias": "Superman",
    "city": "Metrópolis",
    "team": "Liga de la Justicia"
  },
  {
    "id": 2,
    "name": "Tony Stark",
    "alias": "Iron Man",
    "city": "Nueva York",
    "team": "Los Vengadores"
  },
  {
    "id": 3,
    "name": "Bruce Wayne",
    "alias": "Batman",
    "city": "Gotham City",
    "team": "Liga de la Justicia"
  },
  {
    "id": 4,
    "name": "Steve Rogers",
    "alias": "Capitán América",
    "city": "Nueva York",
    "team": "Los Vengadores"
  },
  {
    "id": 5,
    "name": "Diana Prince",
    "alias": "Mujer Maravilla",
    "city": "Themyscira",
    "team": "Liga de la Justicia"
  },
  {
    "id": 6,
    "name": "Thor Odinson",
    "alias": "Thor",
    "city": "Asgard",
    "team": "Los Vengadores"
  },
  {
    "id": 7,
    "name": "Barry Allen",
    "alias": "Flash",
    "city": "Central City",
    "team": "Liga de la Justicia"
  },
  {
    "id": 8,
    "name": "Bruce Banner",
    "alias": "Hulk",
    "city": "Dayton",
    "team": "Los Vengadores"
  },
  {
    "id": 9,
    "name": "Arthur Curry",
    "alias": "Aquaman",
    "city": "Atlantis",
    "team": "Liga de la Justicia"
  },
  {
    "id": 10,
    "name": "Peter Parker",
    "alias": "Spider-Man",
    "city": "Nueva York",
    "team": "Ninguno"
  },
  {
    "id": 11,
    "name": "Hal Jordan",
    "alias": "Linterna Verde",
    "city": "Coast City",
    "team": "Liga de la Justicia"
  },
  {
    "id": 12,
    "name": "Natasha Romanoff",
    "alias": "Viuda Negra",
    "city": "Moscú",
    "team": "Los Vengadores"
  },
  {
    "id": 13,
    "name": "Oliver Queen",
    "alias": "Green Arrow",
    "city": "Star City",
    "team": "Liga de la Justicia"
  },
  {
    "id": 14,
    "name": "Clint Barton",
    "alias": "Ojo de Halcón",
    "city": "Waverly",
    "team": "Los Vengadores"
  },
  {
    "id": 15,
    "name": "Victor Stone",
    "alias": "Cyborg",
    "city": "Detroit",
    "team": "Liga de la Justicia"
  },
  {
    "id": 16,
    "name": "Stephen Vincent Strange",
    "alias": "Doctor Strange",
    "city": "Nueva York",
    "team": "Los Vengadores"
  },
  {
    "id": 17,
    "name": "Billy Batson",
    "alias": "Shazam",
    "city": "Fawcett City",
    "team": "Liga de la Justicia"
  },
  {
    "id": 18,
    "name": "T'Challa",
    "alias": "Black Panther",
    "city": "Wakanda",
    "team": "Los Vengadores"
  },
  {
    "id": 19,
    "name": "Kara Danvers",
    "alias": "Supergirl",
    "city": "National City",
    "team": "Ninguno"
  },
  {
    "id": 20,
    "name": "Wanda Maximoff",
    "alias": "Bruja Escarlata",
    "city": "Transia",
    "team": "Los Vengadores"
  },
  {
    "id": 21,
    "name": "Dick Grayson",
    "alias": "Nightwing",
    "city": "Blüdhaven",
    "team": "Ninguno"
  },
  {
    "id": 22,
    "name": "Charles Xavier",
    "alias": "Profesor X",
    "city": "Salem Center",
    "team": "X-Men"
  },
  {
    "id": 23,
    "name": "Barbara Gordon",
    "alias": "Batgirl",
    "city": "Gotham City",
    "team": "Birds of Prey"
  },
  {
    "id": 24,
    "name": "James Howlett",
    "alias": "Wolverine",
    "city": "Canadá",
    "team": "X-Men"
  },
  {
    "id": 25,
    "name": "J'onn J'onzz",
    "alias": "Detective Marciano",
    "city": "Ninguna",
    "team": "Liga de la Justicia"
  },
  {
    "id": 26,
    "name": "Ororo Munroe",
    "alias": "Tormenta",
    "city": "El Cairo",
    "team": "X-Men"
  },
  {
    "id": 27,
    "name": "Kate Kane",
    "alias": "Batwoman",
    "city": "Gotham City",
    "team": "Ninguno"
  },
  {
    "id": 28,
    "name": "Scott Summers",
    "alias": "Cíclope",
    "city": "Anchorage",
    "team": "X-Men"
  },
  {
    "id": 29,
    "name": "Kyle Rayner",
    "alias": "Linterna Verde",
    "city": "Los Ángeles",
    "team": "Liga de la Justicia"
  },
  {
    "id": 30,
    "name": "Jean Grey",
    "alias": "Fénix",
    "city": "Annandale-on-Hudson",
    "team": "X-Men"
  },

  {
    "id": 31,
    "name": "Bruce Banner",
    "alias": "She-Hulk",
    "city": "Los Ángeles",
    "team": "Los Vengadores"
  },
  {
    "id": 32,
    "name": "Bartholomew Allen",
    "alias": "Kid Flash",
    "city": "Central City",
    "team": "Jóvenes Titanes"
  },
  {
    "id": 33,
    "name": "Matt Murdock",
    "alias": "Daredevil",
    "city": "Hell's Kitchen",
    "team": "Ninguno"
  },
  {
    "id": 34,
    "name": "Jessica Jones",
    "alias": "Jewel",
    "city": "Nueva York",
    "team": "Los Defensores"
  },
  {
    "id": 35,
    "name": "Luke Cage",
    "alias": "Power Man",
    "city": "Harlem",
    "team": "Los Defensores"
  },
  {
    "id": 36,
    "name": "Danny Rand",
    "alias": "Iron Fist",
    "city": "K'un-Lun",
    "team": "Los Defensores"
  },
  {
    "id": 37,
    "name": "Frank Castle",
    "alias": "Punisher",
    "city": "Nueva York",
    "team": "Ninguno"
  },
  {
    "id": 38,
    "name": "Wade Wilson",
    "alias": "Deadpool",
    "city": "Canadá",
    "team": "X-Force"
  },
  {
    "id": 39,
    "name": "Raven Roth",
    "alias": "Raven",
    "city": "Azarath",
    "team": "Jóvenes Titanes"
  },
  {
    "id": 40,
    "name": "Garfield Logan",
    "alias": "Beast Boy",
    "city": "Dakota del Norte",
    "team": "Jóvenes Titanes"
  },
  {
    "id": 41,
    "name": "Koriand'r",
    "alias": "Starfire",
    "city": "Tamaran",
    "team": "Jóvenes Titanes"
  },
  {
    "id": 42,
    "name": "Victor Stone",
    "alias": "Cyborg",
    "city": "Detroit",
    "team": "Jóvenes Titanes"
  },
  {
    "id": 43,
    "name": "Rachel Roth",
    "alias": "Nightstar",
    "city": "Nueva York",
    "team": "Jóvenes Titanes"
  },
  {
    "id": 44,
    "name": "Cassandra Cain",
    "alias": "Batgirl",
    "city": "Gotham City",
    "team": "Birds of Prey"
  },
  {
    "id": 45,
    "name": "Stephanie Brown",
    "alias": "Spoiler",
    "city": "Gotham City",
    "team": "Birds of Prey"
  },
  {
    "id": 46,
    "name": "Selina Kyle",
    "alias": "Catwoman",
    "city": "Gotham City",
    "team": "Ninguno"
  },
  {
    "id": 47,
    "name": "Pamela Isley",
    "alias": "Poison Ivy",
    "city": "Gotham City",
    "team": "Ninguno"
  },
  {
    "id": 48,
    "name": "Harleen Quinzel",
    "alias": "Harley Quinn",
    "city": "Gotham City",
    "team": "Ninguno"
  },
  {
    "id": 49,
    "name": "Jason Todd",
    "alias": "Red Hood",
    "city": "Gotham City",
    "team": "Forajidos"
  },
  {
    "id": 50,
    "name": "Damian Wayne",
    "alias": "Robin",
    "city": "Gotham City",
    "team": "Jóvenes Titanes"
  },
  {
    "id": 51,
    "name": "Jon Kent",
    "alias": "Superboy",
    "city": "Hamilton County",
    "team": "Jóvenes Titanes"
  },
  {
    "id": 52,
    "name": "Kon-El",
    "alias": "Superboy",
    "city": "Hawai",
    "team": "Jóvenes Titanes"
  },
  {
    "id": 53,
    "name": "Billy Kaplan",
    "alias": "Wiccan",
    "city": "Nueva York",
    "team": "Jóvenes Vengadores"
  },
  {
    "id": 54,
    "name": "Teddy Altman",
    "alias": "Hulkling",
    "city": "Nueva York",
    "team": "Jóvenes Vengadores"
  },
  {
    "id": 55,
    "name": "Kamala Khan",
    "alias": "Ms. Marvel",
    "city": "Jersey City",
    "team": "Los Vengadores"
  },
  {
    "id": 56,
    "name": "Miles Morales",
    "alias": "Spider-Man",
    "city": "Brooklyn",
    "team": "Campeones"
  },
  {
    "id": 57,
    "name": "Sam Alexander",
    "alias": "Nova",
    "city": "Carefree",
    "team": "Campeones"
  },
  {
    "id": 58,
    "name": "Riri Williams",
    "alias": "Ironheart",
    "city": "Chicago",
    "team": "Campeones"
  },
  {
    "id": 59,
    "name": "Amadeus Cho",
    "alias": "Brawn",
    "city": "Tucson",
    "team": "Campeones"
  },
  {
    "id": 60,
    "name": "Laura Kinney",
    "alias": "X-23",
    "city": "Instalación La Sala Roja",
    "team": "X-Men"
  },
  
  {
    "id": 61,
    "name": "Clark Kent",
    "alias": "Superboy Prime",
    "city": "Tierra-Prime",
    "team": "Ninguno"
  },
  {
    "id": 62,
    "name": "Jason Rusch",
    "alias": "Firestorm",
    "city": "Nueva York",
    "team": "Liga de la Justicia"
  },
  {
    "id": 63,
    "name": "Jaime Reyes",
    "alias": "Blue Beetle",
    "city": "El Paso",
    "team": "Jóvenes Titanes"
  },
  {
    "id": 64,
    "name": "Babs Gordon",
    "alias": "Oráculo",
    "city": "Gotham City",
    "team": "Birds of Prey"
  },
  {
    "id": 65,
    "name": "Dinah Lance",
    "alias": "Canario Negro",
    "city": "Star City",
    "team": "Liga de la Justicia"
  },
  {
    "id": 66,
    "name": "Kate Bishop",
    "alias": "Hawkeye",
    "city": "Nueva York",
    "team": "Jóvenes Vengadores"
  },
  {
    "id": 67,
    "name": "America Chavez",
    "alias": "Miss America",
    "city": "Utopía Paralela",
    "team": "Jóvenes Vengadores"
  },
  {
    "id": 68,
    "name": "Danny Ketch",
    "alias": "Ghost Rider",
    "city": "Brooklyn",
    "team": "Ninguno"
  },
  {
    "id": 69,
    "name": "Blade",
    "alias": "Blade",
    "city": "Londres",
    "team": "Cazadores de Monstruos"
  },
  {
    "id": 70,
    "name": "Jessica Drew",
    "alias": "Spider-Woman",
    "city": "Londres",
    "team": "Los Vengadores"
  }

]